[
 {
  "docstatus": 0,
  "doctype": "Workflow State",
  "icon": "ok-sign",
  "modified": "2022-10-19 10:10:56.861294",
  "name": "Approved",
  "style": "Success",
  "workflow_state_name": "Approved"
 },
 {
  "docstatus": 0,
  "doctype": "Workflow State",
  "icon": "question-sign",
  "modified": "2022-10-19 10:10:56.858228",
  "name": "Pending",
  "style": "",
  "workflow_state_name": "Pending"
 },
 {
  "docstatus": 0,
  "doctype": "Workflow State",
  "icon": "remove",
  "modified": "2022-10-19 10:10:56.866321",
  "name": "Rejected",
  "style": "Danger",
  "workflow_state_name": "Rejected"
 }
]